openopus/cache.py
openopus/client.py
openopus/errors.py
openopus/models.py
openopus/service.py
openopus-0.0.3.dist-info/licenses/LICENSE
openopus-0.0.3.dist-info/METADATA
openopus-0.0.3.dist-info/WHEEL
openopus-0.0.3.dist-info/top_level.txt
openopus-0.0.3.dist-info/RECORD
