Metadata-Version: 2.4
Name: openopus
Version: 0.0.3
Summary: Python client and service layer for Open Opus API with caching and normalized models
Author-email: Joonbo Shim <joonbo@gmail.com>
License-Expression: MIT
Keywords: Open Opus,classical music,classical
Classifier: Programming Language :: Python
Requires-Python: >=3.10
License-File: LICENSE
Requires-Dist: requests
Dynamic: license-file
